bigquery_agents/.gitignore
bigquery_agents/__init__.py
bigquery_agents/bq_fix/__init__.py
bigquery_agents/bq_fix/__main__.py
bigquery_agents/bq_fix/__pycache__/__init__.cpython-312.pyc
bigquery_agents/bq_fix/__pycache__/__main__.cpython-312.pyc
bigquery_agents/bq_fix_basic/__init__.py
bigquery_agents/bq_fix_basic/__main__.py
bigquery_agents/bq_medic.py
bigquery_agents/graph.jpg
bigquery_agents-0.1.15.dist-info/METADATA
bigquery_agents-0.1.15.dist-info/WHEEL
bigquery_agents-0.1.15.dist-info/entry_points.txt
bigquery_agents-0.1.15.dist-info/RECORD
