Metadata-Version: 2.3
Name: bigquery_agents
Version: 0.1.15
Summary: 
License: Google
Author: sametkaradag
Author-email: sametkaradag@gmail.com
Requires-Python: >=3.12,<4.0
Classifier: License :: Other/Proprietary License
Classifier: Programming Language :: Python :: 3
Classifier: Programming Language :: Python :: 3.12
Classifier: Programming Language :: Python :: 3.13
Requires-Dist: google-cloud-bigquery (>=3.29.0,<4.0.0)
Requires-Dist: langchain (>=0.3.17,<0.4.0)
Requires-Dist: langchain-google-vertexai (>=2.0.12,<3.0.0)
Requires-Dist: langgraph (>=0.2.69,<0.3.0)
